odoo/addons/shopinvader_product_stock_state/README.rst
odoo/addons/shopinvader_product_stock_state/__init__.py
odoo/addons/shopinvader_product_stock_state/__manifest__.py
odoo/addons/shopinvader_product_stock_state/i18n/shopinvader_product_stock_state.pot
odoo/addons/shopinvader_product_stock_state/models/__init__.py
odoo/addons/shopinvader_product_stock_state/models/shopinvader_backend.py
odoo/addons/shopinvader_product_stock_state/models/shopinvader_variant.py
odoo/addons/shopinvader_product_stock_state/tests/__init__.py
odoo/addons/shopinvader_product_stock_state/tests/test_product.py
odoo14_addon_shopinvader_product_stock_state-14.0.1.0.1.dev1.dist-info/METADATA
odoo14_addon_shopinvader_product_stock_state-14.0.1.0.1.dev1.dist-info/WHEEL
odoo14_addon_shopinvader_product_stock_state-14.0.1.0.1.dev1.dist-info/top_level.txt
odoo14_addon_shopinvader_product_stock_state-14.0.1.0.1.dev1.dist-info/RECORD
