Metadata-Version: 2.1
Name: odoo14-addon-shopinvader-product-stock-state
Version: 14.0.1.0.1.dev1
Summary: This module is used to choose a stock state during theexport (by backend)
Home-page: https://github.com/shopinvader/odoo-shopinvader
Author: Akretion
License: AGPL-3
Platform: UNKNOWN
Classifier: Programming Language :: Python
Classifier: Framework :: Odoo
Classifier: License :: OSI Approved :: GNU Affero General Public License v3
Requires-Python: >=3.6
Requires-Dist: odoo14-addon-product-stock-state
Requires-Dist: odoo14-addon-shopinvader-product-stock
Requires-Dist: odoo (<14.1dev,>=14.0a)
